gsapi/GSAPIVersion.py
gsapi/GSBassmineAnalysis.py
gsapi/GSBassmineMarkov.py
gsapi/GSBassmineUtils.py
gsapi/GSDataset.py
gsapi/GSIO.py
gsapi/GSLogging.py
gsapi/GSPattern.py
gsapi/GSPatternUtils.py
gsapi/GSPitchSpelling.py
gsapi/__init__.py
gsapi/GSDescriptors/GSBaseDescriptor.py
gsapi/GSDescriptors/GSDescriptorChord.py
gsapi/GSDescriptors/GSDescriptorDensity.py
gsapi/GSDescriptors/GSDescriptorNumberOfTags.py
gsapi/GSDescriptors/GSDescriptorSyncopation.py
gsapi/GSDescriptors/__init__.py
gsapi/GSFeatureSpaces/GSDensityDrumSpace.py
gsapi/GSFeatureSpaces/__init__.py
gsapi/GSPatternTransformers/AgnosticDensity.py
gsapi/GSPatternTransformers/Chordify.py
gsapi/GSPatternTransformers/GSBasePatternTransformer.py
gsapi/GSPatternTransformers/__init__.py
gsapi/GSStyles/GSBaseStyle.py
gsapi/GSStyles/GSDBStyle.py
gsapi/GSStyles/GSMarkovStyle.py
gsapi/GSStyles/GSMonophonicInterlockingStyle.py
gsapi/GSStyles/__init__.py
gsapi/HighLevelExtractors/__init__.py
gsapi/MathUtils/PatternMarkov.py
gsapi/MathUtils/__init__.py
gsapi/test/AgnosticDensityTest.py
gsapi/test/DescriptorTests.py
gsapi/test/GSIOTest.py
gsapi/test/GSPatternTest.py
gsapi/test/GSPatternTestUtils.py
gsapi/test/GSStylesTest.py
gsapi/test/GSViewpointTest.py
gsapi/test/MarkovPatternTest.py
gsapi/test/__init__.py
gsapi-1.0.3.dist-info/DESCRIPTION.rst
gsapi-1.0.3.dist-info/METADATA
gsapi-1.0.3.dist-info/RECORD
gsapi-1.0.3.dist-info/WHEEL
gsapi-1.0.3.dist-info/metadata.json
gsapi-1.0.3.dist-info/top_level.txt
gsapi-1.0.3.dist-info/zip-safe
m21/__init__.py
m21/fm21.py
