Metadata-Version: 2.0
Name: gsapi
Version: 1.0.3
Summary: Python Symbolic Music Manipulation Tools
Home-page: https://github.com/Giantsteps/gsapi
Author: Martin Hermant, Angel Faraldo, Pere Calopa
Author-email: angel.faraldo@upf.edu
License: UNKNOWN
Platform: UNKNOWN
Requires-Dist: python-midi
